tkintercli/__init__.py
tkintercli/__version__.py
tkintercli/icons.py
tkintercli/main.py
tkintercli/icons/accessibility-outline.svg
tkintercli/icons/accessibility-sharp.svg
tkintercli/icons/accessibility.svg
tkintercli/icons/add-circle-outline.svg
tkintercli/icons/add-circle-sharp.svg
tkintercli/icons/add-circle.svg
tkintercli/icons/add-outline.svg
tkintercli/icons/add-sharp.svg
tkintercli/icons/add.svg
tkintercli/icons/airplane-outline.svg
tkintercli/icons/airplane-sharp.svg
tkintercli/icons/airplane.svg
tkintercli/icons/alarm-outline.svg
tkintercli/icons/alarm-sharp.svg
tkintercli/icons/alarm.svg
tkintercli/icons/albums-outline.svg
tkintercli/icons/albums-sharp.svg
tkintercli/icons/albums.svg
tkintercli/icons/alert-circle-outline.svg
tkintercli/icons/alert-circle-sharp.svg
tkintercli/icons/alert-circle.svg
tkintercli/icons/alert-outline.svg
tkintercli/icons/alert-sharp.svg
tkintercli/icons/alert.svg
tkintercli/icons/american-football-outline.svg
tkintercli/icons/american-football-sharp.svg
tkintercli/icons/american-football.svg
tkintercli/icons/analytics-outline.svg
tkintercli/icons/analytics-sharp.svg
tkintercli/icons/analytics.svg
tkintercli/icons/aperture-outline.svg
tkintercli/icons/aperture-sharp.svg
tkintercli/icons/aperture.svg
tkintercli/icons/apps-outline.svg
tkintercli/icons/apps-sharp.svg
tkintercli/icons/apps.svg
tkintercli/icons/archive-outline.svg
tkintercli/icons/archive-sharp.svg
tkintercli/icons/archive.svg
tkintercli/icons/arrow-back-circle-outline.svg
tkintercli/icons/arrow-back-circle-sharp.svg
tkintercli/icons/arrow-back-circle.svg
tkintercli/icons/arrow-back-outline.svg
tkintercli/icons/arrow-back-sharp.svg
tkintercli/icons/arrow-back.svg
tkintercli/icons/arrow-down-circle-outline.svg
tkintercli/icons/arrow-down-circle-sharp.svg
tkintercli/icons/arrow-down-circle.svg
tkintercli/icons/arrow-down-left-box-outline.svg
tkintercli/icons/arrow-down-left-box-sharp.svg
tkintercli/icons/arrow-down-left-box.svg
tkintercli/icons/arrow-down-outline.svg
tkintercli-1.0.0.dist-info/licenses/LICENSE
tkintercli-1.0.0.dist-info/METADATA
tkintercli-1.0.0.dist-info/WHEEL
tkintercli-1.0.0.dist-info/entry_points.txt
tkintercli-1.0.0.dist-info/top_level.txt
tkintercli-1.0.0.dist-info/RECORD
