Metadata-Version: 2.4
Name: tkintercli
Version: 1.0.0
Summary: TkinterCLI est un outil en ligne de commande permettant de simplfier la création de projet avec Tkinter.
Home-page: https://github.com/Albatros329/atc_tracker/
Author: Albatros329
Requires-Python: >=3.10
License-File: LICENSE
Requires-Dist: click
Requires-Dist: colorama
Requires-Dist: PyYAML
Requires-Dist: setuptools
Requires-Dist: Pillow
Dynamic: author
Dynamic: description
Dynamic: description-content-type
Dynamic: home-page
Dynamic: license-file
Dynamic: requires-dist
Dynamic: requires-python
Dynamic: summary
